twitter_client
