Metadata-Version: 1.0
Name: twitter-client
Version: 0.1a2
Summary: Python client library for Twitter APIs
Home-page: http://makeyjl.blogspot.com/
Author: Yu-Jie Lin
Author-email: livibetter@gmail.com
License: Apache 2.0
Keywords: twitter atom gdata
Platform: UNKNOWN
